CHANGELOG.rst
LICENSE
MANIFEST.in
README.rst
setup.cfg
setup.py
aweber_api/__init__.py
aweber_api/base.py
aweber_api/collection.py
aweber_api/data_dict.py
aweber_api/entry.py
aweber_api/oauth.py
aweber_api/response.py
aweber_api.egg-info/PKG-INFO
aweber_api.egg-info/SOURCES.txt
aweber_api.egg-info/dependency_links.txt
aweber_api.egg-info/requires.txt
aweber_api.egg-info/top_level.txt