Metadata-Version: 1.1
Name: aweber-api
Version: 1.4.0
Summary: A python client library for the AWeber API.
Home-page: https://github.com/aweber/AWeber-API-Python-Library
Author: AWeber API Team
Author-email: api@aweber.com
License: UNKNOWN
Download-URL: http://pypi.python.org/pypi/aweber_api
Platform: UNKNOWN
Classifier: Development Status :: 5 - Production/Stable
Classifier: Intended Audience :: Developers
Classifier: Environment :: Web Environment
Classifier: Operating System :: OS Independent
Classifier: Programming Language :: Python
Classifier: Topic :: Internet :: WWW/HTTP
Classifier: Topic :: Software Development :: Libraries :: Python Modules
Classifier: License :: OSI Approved :: BSD License
